[{"__type__":"cc.AnimationClip","_name":"superEffClip","_duration":0.08333333333333333,"speed":0.2,"wrapMode":2,"curveData":{"comps":{"cc.Sprite":{"spriteFrame":[{"frame":0,"value":{"__uuid__":"08xF7unohNn4/UR6MCGjDP"}},{"frame":0.016666666666666666,"value":{"__uuid__":"c7lw463rJAJIHJOqSl+VMK"}},{"frame":0.03333333333333333,"value":{"__uuid__":"e9dWUG9ylFiaUGheFmqzCy"}},{"frame":0.05,"value":{"__uuid__":"ad/l20P+pAoprMWldrQy9L"}},{"frame":0.06666666666666667,"value":{"__uuid__":"77Fh6MDPZLOJ6dC6QXiZRv"}}]}}}},{"__type__":"cc.SpriteFrame","content":{"name":"1","texture":"17b9b3393","rect":[715,226,166,56],"offset":[-24,-36],"originalSize":[256,128],"rotated":1,"capInsets":[0,0,0,0]}},{"__type__":"cc.SpriteFrame","content":{"name":"5","texture":"17b9b3393","rect":[3,137,229,128],"offset":[8.5,0],"originalSize":[256,128],"capInsets":[0,0,0,0]}},{"__type__":"cc.SpriteFrame","content":{"name":"4","texture":"17b9b3393","rect":[3,3,242,128],"offset":[0,0],"originalSize":[256,128],"capInsets":[0,0,0,0]}},{"__type__":"cc.SpriteFrame","content":{"name":"2","texture":"17b9b3393","rect":[717,3,217,84],"offset":[-12.5,-22],"originalSize":[256,128],"rotated":1,"capInsets":[0,0,0,0]}},{"__type__":"cc.SpriteFrame","content":{"name":"3","texture":"17b9b3393","rect":[486,213,223,128],"offset":[4.5,0],"originalSize":[256,128],"capInsets":[0,0,0,0]}}]