[{"__type__":"cc.Prefab","_name":"eff","data":{"__id__":1}},{"__type__":"cc.Node","_name":"1","_components":[{"__type__":"cc.Sprite","node":{"__id__":1},"_materials":[{"__uuid__":"ecpdLyjvZBwrvm+cedCcQy"}],"_spriteFrame":{"__uuid__":"08xF7unohNn4/UR6MCGjDP"}},{"__type__":"cc.Animation","node":{"__id__":1},"_defaultClip":{"__uuid__":"03D/iZshlKTbDjtofk0ooF"},"_clips":[{"__uuid__":"03D/iZshlKTbDjtofk0ooF"}],"playOnLoad":true}],"_prefab":{"__type__":"cc.PrefabInfo","root":{"__id__":1},"asset":{"__uuid__":"f627/q7zFOM4rSqz8VpEon"},"fileId":"dfHMiQPTVNPKsPzjF4AOzD"},"_contentSize":{"__type__":"cc.Size","width":166,"height":56},"_trs":{"__type__":"TypedArray","ctor":"Float64Array","array":[0,28.679,0,0,0,0,1,1,1,1]}}]